{
  "entries": [
    {
      "phase": "plan",
      "workItemId": "FV-1-373",
      "renderedHash": "71439fa4e2679b6250d04c96c5574c38dbb7ef31fddeb209f06658b5d839ed90",
      "timestamp": "2026-03-17T10:18:52.866306Z",
      "variables": {},
      "charCount": 7518
    },
    {
      "phase": "implement",
      "workItemId": "FV-1-373",
      "renderedHash": "8eb4d9588c437de7d33efcdb079aa2cb7c7768368988203d802c33fb04ea157c",
      "timestamp": "2026-03-17T10:22:48.131086Z",
      "variables": {},
      "charCount": 10020
    },
    {
      "phase": "verify",
      "workItemId": "FV-1-373",
      "renderedHash": "b78d480a66e411b7404b4b17e6af214a2a1ee49eae815f7f3eea4be4125437f8",
      "timestamp": "2026-03-17T10:25:35.125775Z",
      "variables": {},
      "charCount": 16623
    }
  ]
}